autodirs/__init__.py
autodirs/directories.py
autodirs-1.1.0.dist-info/LICENSE
autodirs-1.1.0.dist-info/METADATA
autodirs-1.1.0.dist-info/WHEEL
autodirs-1.1.0.dist-info/top_level.txt
autodirs-1.1.0.dist-info/RECORD
