Metadata-Version: 2.1
Name: autodirs
Version: 1.1.0
Summary: A python project to automatically generate directories and sub-directories
Home-page: https://github.com/pushkarkadam/autodirs
Author: Pushkar Kadam
Author-email: pushkarkadam17@outlook.com
License: UNKNOWN
Platform: UNKNOWN
Classifier: Programming Language :: Python :: 3
Classifier: License :: OSI Approved :: MIT License
Classifier: Operating System :: OS Independent
Requires-Python: >=3.6
License-File: LICENSE
